acache/__init__.py
acache/alru_cache.py
acache/attl_cache.py
acache/cache.py
acache/key.py
python_acache-0.1.4.dist-info/WHEEL
python_acache-0.1.4.dist-info/METADATA
python_acache-0.1.4.dist-info/RECORD
